{"_type":"export","__export_format":4,"__export_date":"2020-02-10T23:11:47.425Z","__export_source":"insomnia.desktop.app:v7.0.6","resources":[{"_id":"req_905af0ef985c4422998892a05d9b29b5","authentication":{},"body":{"mimeType":"application/json","text":"{\n\t\"permissions\": [1],\n\t\"username\": \"luiz_ortega10\",\n\t\"email\": \"luizngust10@gmail.com\",\n\t\"password\": \"123456\"\n}"},"created":1580092771293,"description":"","headers":[{"id":"pair_ffb24e21766346e38d5bd9494acb2c32","name":"Content-Type","value":"application/json"}],"isPrivate":false,"metaSortKey":-1580092113179,"method":"POST","modified":1581124146411,"name":"Create","parameters":[],"parentId":"fld_f7c2da8a3da34981ad45419b110d3d91","settingDisableRenderRequestBody":false,"settingEncodeUrl":true,"settingFollowRedirects":"global","settingRebuildPath":true,"settingSendCookies":true,"settingStoreCookies":true,"url":"{{ base_url  }}/users","_type":"request"},{"_id":"fld_f7c2da8a3da34981ad45419b110d3d91","created":1580092095444,"description":"","environment":{},"environmentPropertyOrder":null,"metaSortKey":-1580092095444,"modified":1580092106420,"name":"Users","parentId":"wrk_c327ba50b98d4b4e85cb84587cd74370","_type":"request_group"},{"_id":"wrk_c327ba50b98d4b4e85cb84587cd74370","created":1580092061388,"description":"","modified":1580092061388,"name":"Adonis-Blog_with_ACL","parentId":null,"_type":"workspace"},{"_id":"req_95680958df3a4c738e8e180e19cb8573","authentication":{"token":"{{ token  }}","type":"bearer"},"body":{"mimeType":"application/json","text":"{\n\t\"roles\": [1],\n\t\"username\": \"luiz_ortega4\",\n\t\"email\": \"luizngust4@gmail.com\",\n\t\"password\": \"123456\" \n}"},"created":1581035415206,"description":"","headers":[{"id":"pair_ffb24e21766346e38d5bd9494acb2c32","name":"Content-Type","value":"application/json"}],"isPrivate":false,"metaSortKey":-1580092113154,"method":"PUT","modified":1581126431173,"name":"Update","parameters":[],"parentId":"fld_f7c2da8a3da34981ad45419b110d3d91","settingDisableRenderRequestBody":false,"settingEncodeUrl":true,"settingFollowRedirects":"global","settingRebuildPath":true,"settingSendCookies":true,"settingStoreCookies":true,"url":"{{ base_url  }}/users/9","_type":"request"},{"_id":"req_25508bb4d68a43928a35d165c2811ad3","authentication":{},"body":{"mimeType":"application/json","text":"{\n\t\"email\": \"luizngust4@gmail.com\",\n\t\"password\": \"123456\"\n}"},"created":1580092113129,"description":"","headers":[{"id":"pair_ffb24e21766346e38d5bd9494acb2c32","name":"Content-Type","value":"application/json"}],"isPrivate":false,"metaSortKey":-1580092113129,"method":"POST","modified":1581126376669,"name":"Create","parameters":[],"parentId":"fld_ffc54f7ee16e4accb32511bbfabb1167","settingDisableRenderRequestBody":false,"settingEncodeUrl":true,"settingFollowRedirects":"global","settingRebuildPath":true,"settingSendCookies":true,"settingStoreCookies":true,"url":"{{ base_url  }}/sessions","_type":"request"},{"_id":"fld_ffc54f7ee16e4accb32511bbfabb1167","created":1580092771285,"description":"","environment":{},"environmentPropertyOrder":null,"metaSortKey":-1579772086418,"modified":1580092771285,"name":"Sessions","parentId":"wrk_c327ba50b98d4b4e85cb84587cd74370","_type":"request_group"},{"_id":"req_a8044de5f10a418c826d8066746ce7b7","authentication":{"token":"{{ token  }}","type":"bearer"},"body":{},"created":1580093636683,"description":"","headers":[],"isPrivate":false,"metaSortKey":-1580092113129,"method":"GET","modified":1580093840404,"name":"Index","parameters":[],"parentId":"fld_168d7e2c633049c2b8532ac9483bf9d2","settingDisableRenderRequestBody":false,"settingEncodeUrl":true,"settingFollowRedirects":"global","settingRebuildPath":true,"settingSendCookies":true,"settingStoreCookies":true,"url":"{{ base_url  }}/posts","_type":"request"},{"_id":"fld_168d7e2c633049c2b8532ac9483bf9d2","created":1580093636676,"description":"","environment":{},"environmentPropertyOrder":null,"metaSortKey":-1579612081905,"modified":1580093636676,"name":"Posts","parentId":"wrk_c327ba50b98d4b4e85cb84587cd74370","_type":"request_group"},{"_id":"req_fa7b2f231b6f4e3997ebd3ad1376213e","authentication":{"token":"{{ token  }}","type":"bearer"},"body":{"mimeType":"application/json","text":"{\n\t\"title\": \"Test Post!\",\n\t\"body\": \"Post Test!\",\n\t\"type\": \"public\"\n}"},"created":1580093954659,"description":"","headers":[{"id":"pair_cfd942195e244265b2824c182579e4b0","name":"Content-Type","value":"application/json"}],"isPrivate":false,"metaSortKey":-1579772100640,"method":"POST","modified":1581124191147,"name":"Create","parameters":[],"parentId":"fld_168d7e2c633049c2b8532ac9483bf9d2","settingDisableRenderRequestBody":false,"settingEncodeUrl":true,"settingFollowRedirects":"global","settingRebuildPath":true,"settingSendCookies":true,"settingStoreCookies":true,"url":"{{ base_url  }}/posts","_type":"request"},{"_id":"req_f2bc9b02972645b3865b6769445063d6","authentication":{"token":"{{ token  }}","type":"bearer"},"body":{},"created":1580094335620,"description":"","headers":[],"isPrivate":false,"metaSortKey":-1579612094395.5,"method":"GET","modified":1581126237961,"name":"Show","parameters":[],"parentId":"fld_168d7e2c633049c2b8532ac9483bf9d2","settingDisableRenderRequestBody":false,"settingEncodeUrl":true,"settingFollowRedirects":"global","settingRebuildPath":true,"settingSendCookies":true,"settingStoreCookies":true,"url":"{{ base_url  }}/posts/1","_type":"request"},{"_id":"req_6def864531d4413e9027ddcd6a5434d6","authentication":{"token":"{{ token  }}","type":"bearer"},"body":{"mimeType":"application/json","text":"{\n\t\"title\": \"Primeiro Post\",\n\t\"body\": \"Post teste!\"\n}"},"created":1580094650425,"description":"","headers":[{"id":"pair_45df72cb43474990a1f7884da1139c66","name":"Content-Type","value":"application/json"}],"isPrivate":false,"metaSortKey":-1579532091273.25,"method":"PUT","modified":1580094681338,"name":"Update","parameters":[],"parentId":"fld_168d7e2c633049c2b8532ac9483bf9d2","settingDisableRenderRequestBody":false,"settingEncodeUrl":true,"settingFollowRedirects":"global","settingRebuildPath":true,"settingSendCookies":true,"settingStoreCookies":true,"url":"{{ base_url  }}/posts/1","_type":"request"},{"_id":"req_ee99845a3cf74eb8a9518f30cc9f3107","authentication":{"token":"{{ token  }}","type":"bearer"},"body":{},"created":1580094727033,"description":"","headers":[],"isPrivate":false,"metaSortKey":-1579492089712.125,"method":"DELETE","modified":1580094763062,"name":"Delete","parameters":[],"parentId":"fld_168d7e2c633049c2b8532ac9483bf9d2","settingDisableRenderRequestBody":false,"settingEncodeUrl":true,"settingFollowRedirects":"global","settingRebuildPath":true,"settingSendCookies":true,"settingStoreCookies":true,"url":"{{ base_url  }}/posts/1","_type":"request"},{"_id":"req_be26d58c9cb748c795ade124f9db36f6","authentication":{"token":"{{ token  }}","type":"bearer"},"body":{},"created":1580095067763,"description":"","headers":[],"isPrivate":false,"metaSortKey":-1580092113129,"method":"GET","modified":1580095251894,"name":"Index","parameters":[],"parentId":"fld_5a07fb4d0f674391ae22f3148738ce4f","settingDisableRenderRequestBody":false,"settingEncodeUrl":true,"settingFollowRedirects":"global","settingRebuildPath":true,"settingSendCookies":true,"settingStoreCookies":true,"url":"{{ base_url  }}/permissions","_type":"request"},{"_id":"fld_5a07fb4d0f674391ae22f3148738ce4f","created":1580095067755,"description":"","environment":{},"environmentPropertyOrder":null,"metaSortKey":-1579532079648.5,"modified":1580095067755,"name":"Permission","parentId":"wrk_c327ba50b98d4b4e85cb84587cd74370","_type":"request_group"},{"_id":"req_7c05b4696a5c4e79846f2370e8663c55","authentication":{"token":"{{ token  }}","type":"bearer"},"body":{"mimeType":"application/json","text":"{\n\t\"name\": \"Read public post\",\n\t\"slug\": \"read_public_posts\",\n\t\"description\": \"Read public post on blog.\"\n}"},"created":1580095067771,"description":"","headers":[{"id":"pair_cfd942195e244265b2824c182579e4b0","name":"Content-Type","value":"application/json"}],"isPrivate":false,"metaSortKey":-1579772100640,"method":"POST","modified":1581126575982,"name":"Create","parameters":[],"parentId":"fld_5a07fb4d0f674391ae22f3148738ce4f","settingDisableRenderRequestBody":false,"settingEncodeUrl":true,"settingFollowRedirects":"global","settingRebuildPath":true,"settingSendCookies":true,"settingStoreCookies":true,"url":"{{ base_url  }}/permissions","_type":"request"},{"_id":"req_57f250dbccde4fa39ca365b76bd63486","authentication":{"token":"{{ token  }}","type":"bearer"},"body":{"mimeType":"application/json","text":"{\n\t \"slug\": \"read_posts\"\n}"},"created":1580095067782,"description":"","headers":[{"id":"pair_45df72cb43474990a1f7884da1139c66","name":"Content-Type","value":"application/json"}],"isPrivate":false,"metaSortKey":-1579532091273.25,"method":"PUT","modified":1581039039591,"name":"Update","parameters":[],"parentId":"fld_5a07fb4d0f674391ae22f3148738ce4f","settingDisableRenderRequestBody":false,"settingEncodeUrl":true,"settingFollowRedirects":"global","settingRebuildPath":true,"settingSendCookies":true,"settingStoreCookies":true,"url":"{{ base_url  }}/permissions/3","_type":"request"},{"_id":"req_5ef33f1b2c90451099d19778ca819363","authentication":{"token":"{{ token  }}","type":"bearer"},"body":{},"created":1580095067784,"description":"","headers":[],"isPrivate":false,"metaSortKey":-1579492089712.125,"method":"DELETE","modified":1580095501541,"name":"Delete","parameters":[],"parentId":"fld_5a07fb4d0f674391ae22f3148738ce4f","settingDisableRenderRequestBody":false,"settingEncodeUrl":true,"settingFollowRedirects":"global","settingRebuildPath":true,"settingSendCookies":true,"settingStoreCookies":true,"url":"{{ base_url  }}/permissions/4","_type":"request"},{"_id":"req_c747db2e6f0e48979a018d2abbfae258","authentication":{"token":"{{ token  }}","type":"bearer"},"body":{},"created":1580777329687,"description":"","headers":[],"isPrivate":false,"metaSortKey":-1580092113129,"method":"GET","modified":1580777339599,"name":"Index","parameters":[],"parentId":"fld_6edb817b580741be8aa6f8e779127ef6","settingDisableRenderRequestBody":false,"settingEncodeUrl":true,"settingFollowRedirects":"global","settingRebuildPath":true,"settingSendCookies":true,"settingStoreCookies":true,"url":"{{ base_url  }}/roles","_type":"request"},{"_id":"fld_6edb817b580741be8aa6f8e779127ef6","created":1580777329678,"description":"","environment":{},"environmentPropertyOrder":null,"metaSortKey":-1579492078520.25,"modified":1580777329678,"name":"Roles","parentId":"wrk_c327ba50b98d4b4e85cb84587cd74370","_type":"request_group"},{"_id":"req_bcc4709b012f4fa791af7487b3ae232c","authentication":{"token":"{{ token  }}","type":"bearer"},"body":{},"created":1580777879546,"description":"","headers":[],"isPrivate":false,"metaSortKey":-1579932106884.5,"method":"GET","modified":1581036613187,"name":"Get","parameters":[],"parentId":"fld_6edb817b580741be8aa6f8e779127ef6","settingDisableRenderRequestBody":false,"settingEncodeUrl":true,"settingFollowRedirects":"global","settingRebuildPath":true,"settingSendCookies":true,"settingStoreCookies":true,"url":"{{ base_url  }}/roles/3","_type":"request"},{"_id":"req_30d1de8f2c094389b31c8e00417ead8f","authentication":{"token":"{{ token  }}","type":"bearer"},"body":{"mimeType":"application/json","text":"{\n\t\"name\": \"Moderator\",\n\t\"slug\": \"moderator\",\n\t\"description\": \"Blog's Moderator.\",\n\t\"permissions\": [1,2,3,4]\n}"},"created":1580777329697,"description":"","headers":[{"id":"pair_cfd942195e244265b2824c182579e4b0","name":"Content-Type","value":"application/json"}],"isPrivate":false,"metaSortKey":-1579772100640,"method":"POST","modified":1581123806476,"name":"Create","parameters":[],"parentId":"fld_6edb817b580741be8aa6f8e779127ef6","settingDisableRenderRequestBody":false,"settingEncodeUrl":true,"settingFollowRedirects":"global","settingRebuildPath":true,"settingSendCookies":true,"settingStoreCookies":true,"url":"{{ base_url  }}/roles","_type":"request"},{"_id":"req_30b9b4c3534e43308d7334be8fc74b70","authentication":{"token":"{{ token  }}","type":"bearer"},"body":{"mimeType":"application/json","text":"{\n\t\"permissions\": [1,2,3,4,5,6]\n}"},"created":1580777329704,"description":"","headers":[{"id":"pair_45df72cb43474990a1f7884da1139c66","name":"Content-Type","value":"application/json"}],"isPrivate":false,"metaSortKey":-1579532091273.25,"method":"PUT","modified":1581126631335,"name":"Update","parameters":[],"parentId":"fld_6edb817b580741be8aa6f8e779127ef6","settingDisableRenderRequestBody":false,"settingEncodeUrl":true,"settingFollowRedirects":"global","settingRebuildPath":true,"settingSendCookies":true,"settingStoreCookies":true,"url":"{{ base_url  }}/roles/1","_type":"request"},{"_id":"req_c05efbaa461146a6b61e9329e17a26a4","authentication":{"token":"{{ token  }}","type":"bearer"},"body":{},"created":1580777329706,"description":"","headers":[],"isPrivate":false,"metaSortKey":-1579492089712.125,"method":"DELETE","modified":1580777836739,"name":"Delete","parameters":[],"parentId":"fld_6edb817b580741be8aa6f8e779127ef6","settingDisableRenderRequestBody":false,"settingEncodeUrl":true,"settingFollowRedirects":"global","settingRebuildPath":true,"settingSendCookies":true,"settingStoreCookies":true,"url":"{{ base_url  }}/roles/3","_type":"request"},{"_id":"env_5465997dc065f823484f4391a36518d2be90a362","color":null,"created":1580092061512,"data":{"base_url":"http://127.0.0.1:3333","token":"eyJhbGciOiJIUzI1NiIsInR5cCI6IkpXVCJ9.eyJ1aWQiOjksImlhdCI6MTU4MTEyNjM3N30.MfCvXsoRl83z053merdUBKzogNqRJDuIkiozQCbpI3w"},"dataPropertyOrder":{"&":["base_url","token"]},"isPrivate":false,"metaSortKey":1580092061512,"modified":1581126389857,"name":"Base Environment","parentId":"wrk_c327ba50b98d4b4e85cb84587cd74370","_type":"environment"},{"_id":"jar_5465997dc065f823484f4391a36518d2be90a362","cookies":[],"created":1580092061514,"modified":1580092061514,"name":"Default Jar","parentId":"wrk_c327ba50b98d4b4e85cb84587cd74370","_type":"cookie_jar"}]}